__init__.py
mishmash_io_auth_jwt.py
mishmash_io_auth_jwt-0.0.2.dist-info/LICENSE
mishmash_io_auth_jwt-0.0.2.dist-info/METADATA
mishmash_io_auth_jwt-0.0.2.dist-info/WHEEL
mishmash_io_auth_jwt-0.0.2.dist-info/top_level.txt
mishmash_io_auth_jwt-0.0.2.dist-info/RECORD
