Metadata-Version: 2.1
Name: mishmash-io-auth-jwt
Version: 0.0.2
Summary: mishmash io auth jwt plugin
Home-page: https://mishmash.io
Author: mishmash.io
Author-email: info@mishmash.io
License: Apache License v2.0
Project-URL: Bug Tracker, https://github.com/mishmash-io/mishmash-io-auth-plugins/tree/main/python/mishmash-io-auth-jwt/issues
Project-URL: Documentation, https://mishmash.io
Project-URL: Source Code, https://github.com/mishmash-io/mishmash-io-auth-plugins/tree/main/python/mishmash-io-auth-jwt
Keywords: database,artificial intelligence,development
Platform: UNKNOWN
Classifier: Intended Audience :: Developers
Classifier: License :: OSI Approved :: Apache Software License
Classifier: Programming Language :: Python
Classifier: Programming Language :: Python :: 3 :: Only
Classifier: Programming Language :: Python :: 3.6
Classifier: Programming Language :: Python :: 3.7
Classifier: Programming Language :: Python :: 3.8
Classifier: Development Status :: 3 - Alpha
Classifier: Topic :: Database
Classifier: Topic :: Utilities
Classifier: Topic :: Scientific/Engineering :: Artificial Intelligence
Classifier: Topic :: Scientific/Engineering :: Information Analysis
Classifier: Topic :: Scientific/Engineering :: Interface Engine/Protocol Translator
Classifier: Topic :: Scientific/Engineering :: Mathematics
Classifier: Topic :: Software Development
Classifier: Topic :: Software Development :: Libraries
Requires-Python: >=3.6, <4
License-File: LICENSE
Requires-Dist: requests
Requires-Dist: pyjwt[crypto]
Requires-Dist: pycryptodome
Provides-Extra: dev
Requires-Dist: pytest ; extra == 'dev'
